[
 {
  "名前": "まぐろ",
  "高値": "-",
  "中値": "3,000",
  "場所": "三重県"
 },
 {
  "名前": "まぐろ",
  "高値": "3,000",
  "中値": "-",
  "場所": "高知県"
 },
 {
  "名前": "びんなが",
  "高値": "1,400",
  "中値": "1,370",
  "場所": "和歌山県"
 },
 {
  "名前": "めばち",
  "高値": "-",
  "中値": "4,250",
  "場所": "三重県"
 },
 {
  "名前": "きわだ",
  "高値": "2,500",
  "中値": "2,100",
  "場所": "ｲﾝﾄﾞﾈｼｱ共和国"
 },
 {
  "名前": "めじ",
  "高値": "-",
  "中値": "1,300",
  "場所": "富山県"
 },
 {
  "名前": "めじ",
  "高値": "-",
  "中値": "700",
  "場所": "鳥取県"
 },
 {
  "名前": "まかじき",
  "高値": "-",
  "中値": "700",
  "場所": "沖縄県"
 },
 {
  "名前": "ばしょうかじき",
  "高値": "700",
  "中値": "-",
  "場所": "沖縄県"
 },
 {
  "名前": "ひらまさ",
  "高値": "1,300",
  "中値": "600",
  "場所": "福井県"
 },
 {
  "名前": "ひらまさ",
  "高値": "503",
  "中値": "450",
  "場所": "島根県"
 },
 {
  "名前": "かんぱち",
  "高値": "-",
  "中値": "1,900",
  "場所": "大分県"
 },
 {
  "名前": "かんぱち",
  "高値": "-",
  "中値": "1,850",
  "場所": "鹿児島県"
 },
 {
  "名前": "ぶり",
  "高値": "400",
  "中値": "-",
  "場所": "福井県"
 },
 {
  "名前": "養殖　ぶり",
  "高値": "1,235",
  "中値": "1,100",
  "場所": "愛媛県"
 },
 {
  "名前": "養殖　ぶり",
  "高値": "1,250",
  "中値": "1,230",
  "場所": "高知県"
 },
 {
  "名前": "わらさ",
  "高値": "-",
  "中値": "550",
  "場所": "福井県"
 },
 {
  "名前": "養殖　わらさ",
  "高値": "1,400",
  "中値": "-",
  "場所": "大分県"
 },
 {
  "名前": "かつお",
  "高値": "1,500",
  "中値": "-",
  "場所": "福井県"
 },
 {
  "名前": "かつお",
  "高値": "1,100",
  "中値": "600",
  "場所": "千葉県"
 },
 {
  "名前": "さば",
  "高値": "278",
  "中値": "-",
  "場所": "千葉県"
 },
 {
  "名前": "さば",
  "高値": "309",
  "中値": "-",
  "場所": "三重県"
 },
 {
  "名前": "さわら",
  "高値": "1,000",
  "中値": "500",
  "場所": "福井県"
 },
 {
  "名前": "あじ",
  "高値": "1,333",
  "中値": "200",
  "場所": "福井県"
 },
 {
  "名前": "あじ",
  "高値": "440",
  "中値": "-",
  "場所": "山口県"
 },
 {
  "名前": "養殖　あじ",
  "高値": "1,900",
  "中値": "-",
  "場所": "愛媛県"
 },
 {
  "名前": "さけ",
  "高値": "-",
  "中値": "1,400",
  "場所": "ｵｰｽﾄﾗﾘｱ"
 },
 {
  "名前": "さけ",
  "高値": "1,400",
  "中値": "-",
  "場所": "ｶﾅﾀﾞ"
 },
 {
  "名前": "たい",
  "高値": "1,700",
  "中値": "800",
  "場所": "福井県"
 },
 {
  "名前": "たい",
  "高値": "-",
  "中値": "500",
  "場所": "石川県"
 },
 {
  "名前": "養殖　たい",
  "高値": "1,400",
  "中値": "850",
  "場所": "三重県"
 },
 {
  "名前": "養殖　たい",
  "高値": "1,400",
  "中値": "1,300",
  "場所": "愛媛県"
 },
 {
  "名前": "甘だい",
  "高値": "-",
  "中値": "1,500",
  "場所": "石川県"
 },
 {
  "名前": "すすき",
  "高値": "1,333",
  "中値": "700",
  "場所": "福井県"
 },
 {
  "名前": "ひらめ",
  "高値": "1,300",
  "中値": "-",
  "場所": "宮城県"
 },
 {
  "名前": "ひらめ",
  "高値": "2,400",
  "中値": "2,400",
  "場所": "愛媛県"
 },
 {
  "名前": "赤がれい",
  "高値": "-",
  "中値": "500",
  "場所": "北海道"
 },
 {
  "名前": "するめいか",
  "高値": "760",
  "中値": "-",
  "場所": "石川県"
 },
 {
  "名前": "まいか",
  "高値": "2,500",
  "中値": "979",
  "場所": "福井県"
 },
 {
  "名前": "まいか",
  "高値": "2,125",
  "中値": "1,625",
  "場所": "長崎県"
 },
 {
  "名前": "たこ",
  "高値": "-",
  "中値": "1,904",
  "場所": "福井県"
 },
 {
  "名前": "たこ",
  "高値": "-",
  "中値": "1,958",
  "場所": "新潟県"
 },
 {
  "名前": "赤えび",
  "高値": "3,333",
  "中値": "2,000",
  "場所": "福井県"
 },
 {
  "名前": "赤えび",
  "高値": "2,303",
  "中値": "-",
  "場所": "北海道"
 },
 {
  "名前": "かき",
  "高値": "-",
  "中値": "667",
  "場所": "鳥取県"
 },
 {
  "名前": "さざえ",
  "高値": "670",
  "中値": "-",
  "場所": "福井県"
 },
 {
  "名前": "さざえ",
  "高値": "-",
  "中値": "500",
  "場所": "石川県"
 },
 {
  "名前": "あわび",
  "高値": "-",
  "中値": "5,800",
  "場所": "大韓民国"
 },
 {
  "名前": "さんま",
  "高値": "-",
  "中値": "550",
  "場所": "北海道"
 },
 {
  "名前": "さんま",
  "高値": "-",
  "中値": "463",
  "場所": "千葉県"
 },
 {
  "名前": "いわし",
  "高値": "-",
  "中値": "250",
  "場所": "宮城県"
 },
 {
  "名前": "いわし",
  "高値": "300",
  "中値": "-",
  "場所": "千葉県"
 },
 {
  "名前": "とびうお",
  "高値": "1,250",
  "中値": "1,000",
  "場所": "福井県"
 },
 {
  "名前": "しいら",
  "高値": "460",
  "中値": "400",
  "場所": "福井県"
 },
 {
  "名前": "にぎす",
  "高値": "500",
  "中値": "-",
  "場所": "石川県"
 },
 {
  "名前": "はたはた",
  "高値": "-",
  "中値": "1,325",
  "場所": "兵庫県"
 },
 {
  "名前": "あなご",
  "高値": "-",
  "中値": "800",
  "場所": "福島県"
 },
 {
  "名前": "あなご",
  "高値": "2,938",
  "中値": "-",
  "場所": "山口県"
 },
 {
  "名前": "冷凍まぐろ",
  "高値": "5,250",
  "中値": "5,250",
  "場所": "ﾏﾙﾀ共和国"
 },
 {
  "名前": "冷凍まぐろ",
  "高値": "-",
  "中値": "3,300",
  "場所": "その他"
 },
 {
  "名前": "冷凍めばち",
  "高値": "2,917",
  "中値": "1,700",
  "場所": "静岡県"
 },
 {
  "名前": "冷凍めばち",
  "高値": "2,200",
  "中値": "-",
  "場所": "台湾"
 },
 {
  "名前": "冷凍きわだ",
  "高値": "2,250",
  "中値": "1,800",
  "場所": "静岡県"
 },
 {
  "名前": "冷凍きわだ",
  "高値": "-",
  "中値": "1,900",
  "場所": "ｾｲｼｪﾙ共和国"
 },
 {
  "名前": "冷凍まかじき",
  "高値": "-",
  "中値": "1,300",
  "場所": "大韓民国"
 },
 {
  "名前": "冷凍するめいか",
  "高値": "-",
  "中値": "945",
  "場所": "石川県"
 },
 {
  "名前": "冷凍するめいか",
  "高値": "-",
  "中値": "580",
  "場所": "ﾆｭｰｼﾞｰﾗﾝﾄﾞ"
 },
 {
  "名前": "冷凍やりいか",
  "高値": "-",
  "中値": "2,579",
  "場所": "ﾓﾛｯｺ王国"
 },
 {
  "名前": "冷凍やりいか",
  "高値": "2,429",
  "中値": "-",
  "場所": "ﾍﾞﾄﾅﾑ社会主義共和国"
 },
 {
  "名前": "冷凍煮だこ",
  "高値": "1,550",
  "中値": "1,380",
  "場所": "北海道"
 },
 {
  "名前": "冷凍赤えび",
  "高値": "-",
  "中値": "950",
  "場所": "ｶﾅﾀﾞ"
 },
 {
  "名前": "冷凍赤えび",
  "高値": "-",
  "中値": "1,950",
  "場所": "ﾛｼｱ連邦"
 },
 {
  "名前": "冷凍ずわいがに",
  "高値": "-",
  "中値": "2,600",
  "場所": "ｶﾅﾀﾞ"
 },
 {
  "名前": "冷凍さば",
  "高値": "600",
  "中値": "600",
  "場所": "千葉県"
 },
 {
  "名前": "冷凍さば",
  "高値": "900",
  "中値": "450",
  "場所": "ﾉﾙｳｪｰ王国"
 },
 {
  "名前": "冷凍銀だら",
  "高値": "2,000",
  "中値": "800",
  "場所": "ｱﾒﾘｶ合衆国"
 },
 {
  "名前": "冷凍赤魚",
  "高値": "-",
  "中値": "800",
  "場所": "ｶﾅﾀﾞ"
 },
 {
  "名前": "冷凍赤魚",
  "高値": "1,143",
  "中値": "1,143",
  "場所": "ﾉﾙｳｪｰ王国"
 },
 {
  "名前": "塩ます",
  "高値": "827",
  "中値": "827",
  "場所": "北海道"
 },
 {
  "名前": "塩すけこ",
  "高値": "-",
  "中値": "3,500",
  "場所": "福岡県"
 },
 {
  "名前": "塩すけこ",
  "高値": "3,000",
  "中値": "1,900",
  "場所": "ｱﾒﾘｶ･ﾛｼｱ"
 },
 {
  "名前": "塩うに",
  "高値": "-",
  "中値": "20,500",
  "場所": "大韓民国"
 },
 {
  "名前": "身欠にしん",
  "高値": "1,350",
  "中値": "1,300",
  "場所": "ﾛｼｱ連邦"
 },
 {
  "名前": "身欠にしん",
  "高値": "1,450",
  "中値": "850",
  "場所": "ｱﾒﾘｶ合衆国"
 },
 {
  "名前": "干するめ",
  "高値": "-",
  "中値": "3,300",
  "場所": "北海道"
 },
 {
  "名前": "ちりめん",
  "高値": "-",
  "中値": "764",
  "場所": "宮城県"
 },
 {
  "名前": "ちりめん",
  "高値": "-",
  "中値": "6,333",
  "場所": "鹿児島県"
 }
]